moodle/__init__.py
moodle/calendar.py
moodle/course.py
moodle/modulebase.py
moodle/moodle.py
moodle/resources.py
moodle/siteinfo.py
moodle/util.py
moodle_mobile_py-1.0.3.dist-info/LICENSE
moodle_mobile_py-1.0.3.dist-info/METADATA
moodle_mobile_py-1.0.3.dist-info/WHEEL
moodle_mobile_py-1.0.3.dist-info/top_level.txt
moodle_mobile_py-1.0.3.dist-info/RECORD
