Metadata-Version: 2.1
Name: moodle-mobile-py
Version: 1.0.3
Summary: A Python Wrapper for the Moodle Mobile API
Home-page: https://github.com/xImAnton/moodle.py
Author: xImAnton_
Author-email: admin@ximanton.de
License: UNKNOWN
Project-URL: Bug Tracker, https://github.com/xImAnton/moodle.py/issues
Platform: UNKNOWN
Classifier: Programming Language :: Python :: 3
Classifier: License :: OSI Approved :: MIT License
Classifier: Operating System :: OS Independent
Requires-Python: >=3.8
License-File: LICENSE
Requires-Dist: aiofiles (==0.8.0)
Requires-Dist: aiohttp (==3.8.1)
